atomicx-0.0.15.dist-info/METADATA
atomicx-0.0.15.dist-info/WHEEL
atomicx-0.0.15.dist-info/licenses/LICENSE
atomicx/__init__.py
atomicx/__init__.pyi
atomicx/atomicx.abi3.so
atomicx/py.typed
atomicx-0.0.15.dist-info/RECORD
