Metadata-Version: 2.4
Name: atomicx
Version: 0.0.15
Classifier: Programming Language :: Rust
Classifier: Programming Language :: Python :: Implementation :: CPython
Classifier: Programming Language :: Python :: Implementation :: PyPy
Classifier: Topic :: Utilities
Classifier: License :: OSI Approved :: MIT License
Classifier: Typing :: Typed
License-File: LICENSE
Summary: easy-to-use lock-free atomic integers, booleans, and floats for Python
Author-email: RuneBlaze <liubaqiao@gmail.com>
Requires-Python: >=3.8
Project-URL: Homepage, https://github.com/RuneBlaze/atomicx
Project-URL: Bug Tracker, https://github.com/RuneBlaze/atomicx/issues
Project-URL: Documentation, https://github.com/RuneBlaze/atomicx/blob/main/DOCS.md
